djparakeet/urls.py
djparakeet/__init__.py
djparakeet/routing.py
djparakeet/views.py
djparakeet/api.py
djparakeet/admin.py
djparakeet/consumers.py
djparakeet/tests.py
djparakeet/models.py
djparakeet/apps.py
djparakeet/migrations/__init__.py
djparakeet/migrations/0001_initial.py
django_parakeet/settings.py
django_parakeet/urls.py
django_parakeet/__init__.py
django_parakeet/routing.py
django_parakeet/wsgi.py
django_parakeet-0.1.dist-info/DESCRIPTION.rst
django_parakeet-0.1.dist-info/METADATA
django_parakeet-0.1.dist-info/metadata.json
django_parakeet-0.1.dist-info/WHEEL
django_parakeet-0.1.dist-info/RECORD
django_parakeet-0.1.dist-info/top_level.txt
util/__init__.py
util/views.py
util/admin.py
util/tests.py
util/models.py
util/apps.py
util/migrations/__init__.py
