Metadata-Version: 2.0
Name: django-parakeet
Version: 0.1
Summary: A simple Django chat application.
Home-page: https://emakarov.github.io/django-parakeet/
Author: Evgeni Makarov
Author-email: evgeni.makarov@gmail.com
License: BSD License
Platform: UNKNOWN
Classifier: Environment :: Web Environment
Classifier: Framework :: Django
Classifier: Framework :: Django :: 1.10
Classifier: Intended Audience :: Developers
Classifier: License :: OSI Approved :: BSD License
Classifier: Operating System :: OS Independent
Classifier: Programming Language :: Python
Classifier: Programming Language :: Python :: 2.7
Classifier: Topic :: Internet :: WWW/HTTP
Classifier: Topic :: Internet :: WWW/HTTP :: Dynamic Content
Requires-Dist: channels
Requires-Dist: django-tastypie
